chm/__init__.py
chm/_chmlib.so
chm/chm.py
chm/chmlib.py
chm/extra.so
pychm-0.8.4.1.dist-info/DESCRIPTION.rst
pychm-0.8.4.1.dist-info/METADATA
pychm-0.8.4.1.dist-info/metadata.json
pychm-0.8.4.1.dist-info/RECORD
pychm-0.8.4.1.dist-info/top_level.txt
pychm-0.8.4.1.dist-info/WHEEL
