Metadata-Version: 2.0
Name: pychm
Version: 0.8.4.1
Summary: Python package to handle CHM files
Home-page: https://github.com/dottedmag/pychm
Author: Mikhail Gusarov
Author-email: dottedmag@dottedmag.net
License: GPL
Platform: UNKNOWN
